<annotation>
	<folder>Toys</folder>
	<filename>Toys_214.jpeg</filename>
	<path>/Users/sahba/Projects/comp473-final-project/training_images/Toys/Toys_214.jpeg</path>
	<source>
		<database>Unknown</database>
	</source>
	<size>
		<width>1920</width>
		<height>2560</height>
		<depth>3</depth>
	</size>
	<segmented>0</segmented>
	<object>
		<name>toy</name>
		<pose>Unspecified</pose>
		<truncated>0</truncated>
		<difficult>0</difficult>
		<bndbox>
			<xmin>649</xmin>
			<ymin>387</ymin>
			<xmax>1320</xmax>
			<ymax>1171</ymax>
		</bndbox>
	</object>
</annotation>
